starco/__init__.py
starco/cloudflare/__init__.py
starco/crypto_gates/__init__.py
starco/crypto_gates/nowpayments/__init__.py
starco/db/__init__.py
starco/debug/__init__.py
starco/gateways/__init__.py
starco/gateways/gates/__init__.py
starco/gateways/gates/aqayepardakht.py
starco/gateways/gates/idpay.py
starco/gateways/gates/nextpay.py
starco/gateways/gates/utils.py
starco/gateways/gates/vandar.py
starco/gateways/gates/zibalpay.py
starco/gui/__init__.py
starco/gui/utils.py
starco/hetzner/__init__.py
starco/pkl/__init__.py
starco/proxy/__init__.py
starco/proxy/utils.py
starco/scraper/__init__.py
starco/tlg/__init__.py
starco/tlg/app/__init__.py
starco/tlg/app/utils.py
starco/tlg/bot/__init__.py
starco/tlg/bot/base.py
starco/tlg/bot/classes.py
starco/tlg/bot/util/__init__.py
starco/tlg/bot/util/enum.py
starco/tlg/bot/util/filteres.py
starco/tlg/bot/util/force_join.py
starco/tlg/bot/util/functions.py
starco/tlg/bot/util/packs.py
starco/tlg/bot/util/time_functions.py
starco/utils/__init__.py
starco/utils/directories.py
starco/utils/ext.py
starco/utils/process.py
starco/utils/scheduler.py
starco/utils/structures.py
starco/utils/time.py
starco/wp_api/__init__.py
starco/wscraper/__init__.py
starco/xray_connctor/__init__.py
Starco-5.0.1.dist-info/METADATA
Starco-5.0.1.dist-info/WHEEL
Starco-5.0.1.dist-info/top_level.txt
Starco-5.0.1.dist-info/RECORD
