Metadata-Version: 2.1
Name: Starco
Version: 5.0.1
Author: Mojtaba Tahmasbi
Requires-Dist: cffi
Requires-Dist: cryptography
Requires-Dist: pycparser ==2.21
Requires-Dist: beautifulsoup4 ==4.12.2
Requires-Dist: lxml ==4.9.3
Requires-Dist: requests
Requires-Dist: easy-db ==0.9.15
Requires-Dist: hcloud ==1.32.0
Requires-Dist: cloudflare ==2.11.6
Requires-Dist: python-socks ==2.4.3
Requires-Dist: python-telegram-bot ==13.14
Requires-Dist: Telethon ==1.33.1
Requires-Dist: phonenumbers
Requires-Dist: pycountry
Requires-Dist: nest-asyncio ==1.5.8
Requires-Dist: zibal
Requires-Dist: nowpayments
Requires-Dist: jdatetime
Requires-Dist: deep-translator
Requires-Dist: async-timeout
Requires-Dist: PySocks
Requires-Dist: selenium ==4.17.2
Requires-Dist: pyperclip ==1.8.2
Requires-Dist: pandas
Requires-Dist: starco-utility
